sylriekit/API.py
sylriekit/C.py
sylriekit/Cache.py
sylriekit/Constants.py
sylriekit/Database.py
sylriekit/Files.py
sylriekit/Git.py
sylriekit/GoLang.py
sylriekit/InlinePython.py
sylriekit/LLM.py
sylriekit/Log.py
sylriekit/Mcp.py
sylriekit/Nim.py
sylriekit/Process.py
sylriekit/Profiler.py
sylriekit/Rust.py
sylriekit/Schedule.py
sylriekit/Security.py
sylriekit/SharedStore.py
sylriekit/TTS.py
sylriekit/Template.py
sylriekit/Website.py
sylriekit/Window.py
sylriekit/__init__.py
sylriekit-0.23.7.dist-info/licenses/LICENSE
sylriekit-0.23.7.dist-info/METADATA
sylriekit-0.23.7.dist-info/WHEEL
sylriekit-0.23.7.dist-info/top_level.txt
sylriekit-0.23.7.dist-info/RECORD
