Metadata-Version: 2.4
Name: sylriekit
Version: 0.23.7
Summary: A personal Python toolbox of utilities.
Author: Kasterfly
License: MIT License
Requires-Python: >=3.12
License-File: LICENSE
Requires-Dist: dill
Requires-Dist: fastmcp
Requires-Dist: flask
Requires-Dist: gunicorn
Requires-Dist: requests
Requires-Dist: cryptography
Requires-Dist: PyJWT
Requires-Dist: boto3
Requires-Dist: psycopg2-binary
Requires-Dist: mysql-connector-python
Requires-Dist: watchdog
Requires-Dist: webviewpy
Requires-Dist: redis
Requires-Dist: RestrictedPython
Requires-Dist: tiktoken
Requires-Dist: miniaudio
Requires-Dist: dotenv
Dynamic: license-file
